README.rst
setup.py
src/mime_streamer/__init__.py
src/mime_streamer/exceptions.py
src/mime_streamer/mime_response_streamer.py
src/mime_streamer/mime_streamer.py
src/mime_streamer/utils.py
src/mime_streamer.egg-info/PKG-INFO
src/mime_streamer.egg-info/SOURCES.txt
src/mime_streamer.egg-info/dependency_links.txt
src/mime_streamer.egg-info/top_level.txt