Metadata-Version: 1.1
Name: mime-streamer
Version: 0.2.0
Summary: Stream IO for multipart MIME content
Home-page: https://github.com/okomestudio/mime-streamer
Author: Taro Sato
Author-email: okomestudio@gmail.com
License: MIT
Platform: Linux
Classifier: Development Status :: 3 - Alpha
Classifier: Intended Audience :: Developers
Classifier: License :: OSI Approved :: MIT License
Classifier: Operating System :: POSIX :: Linux
Classifier: Programming Language :: Python :: 2.7
Classifier: Topic :: Utilities
